qsharp/__init__.py
qsharp/azure.py
qsharp/config.py
qsharp/experimental.py
qsharp/ipython_magic.py
qsharp/loader.py
qsharp/noise_model.py
qsharp/packages.py
qsharp/projects.py
qsharp/qobj.py
qsharp/serialization.py
qsharp/tomography.py
qsharp/types.py
qsharp/utils.py
qsharp/version.py
qsharp/clients/__init__.py
qsharp/clients/iqsharp.py
qsharp/clients/mock.py
qsharp/tests/__init__.py
qsharp/tests/test_azure.py
qsharp/tests/test_iqsharp.py
qsharp/tests/test_loader.py
qsharp/tests/test_serialization.py
qsharp/tests/utils.py
qsharp_core-0.25.218240.dist-info/METADATA
qsharp_core-0.25.218240.dist-info/WHEEL
qsharp_core-0.25.218240.dist-info/top_level.txt
qsharp_core-0.25.218240.dist-info/RECORD
