Metadata-Version: 2.1
Name: qsharp-core
Version: 0.25.218240
Summary: Python client for Q#, a domain-specific quantum programming language
Home-page: https://github.com/microsoft/iqsharp
Author: Microsoft
Author-email: que-contacts@microsoft.com
License: UNKNOWN
Platform: UNKNOWN
Classifier: Programming Language :: Python :: 3
Classifier: License :: OSI Approved :: MIT License
Classifier: Operating System :: OS Independent
Requires-Dist: jupyter-client (<7.0)
Requires-Dist: pyzmq (<20.0.0)
Requires-Dist: traitlets (!=5.2.2)
